regex_match/__init__.py
regex_match/factory.py
regex_match/migrations/0001_initial.py
regex_match/migrations/0002_modelrule_priority.py
regex_match/migrations/0003_auto_20151110_1315.py
regex_match/migrations/0004_auto_20151112_1808.py
regex_match/migrations/0005_auto_20151117_2133.py
regex_match/migrations/0006_auto_20160916_1428.py
regex_match/migrations/0007_auto_20200715_1610.py
regex_match/migrations/__init__.py
regex_match/models/__init__.py
regex_match/models/exception_parser.py
regex_match/models/matching_rule.py
regex_match/models/model_exception.py
regex_match/models/model_rule.py
regex_match/models/parser.py
regex_match/models/parser_method.py
regex_match/models/regex_rule.py
regex_match/objects/__init__.py
regex_match/objects/exception_parser.py
regex_match/objects/model_matcher.py
regex_match/objects/url_to_matching_rule.py
regex_match/objects/parsers/__init__.py
regex_match/objects/parsers/url.py
regex_match/objects/parsers/url_parser.py
django_regex_match-0.2.13.dist-info/METADATA
django_regex_match-0.2.13.dist-info/WHEEL
django_regex_match-0.2.13.dist-info/top_level.txt
django_regex_match-0.2.13.dist-info/RECORD
