Metadata-Version: 2.1
Name: django-regex-match
Version: 0.2.13
Home-page: http://www.admetricks.com/
Author: Dev Admx
Author-email: dev@admetricks.com
Classifier: Environment :: Web Environment
Classifier: Framework :: Django
Classifier: Intended Audience :: Developers
Classifier: License :: OSI Approved :: BSD License
Classifier: Operating System :: OS Independent
Classifier: Programming Language :: Python
Requires-Dist: inflection >=0.3.0
Requires-Dist: django-polymorphic ==1.3
Requires-Dist: funcy ==1.4
Requires-Dist: purl ==1.0.3
Requires-Dist: toolz ==0.12.0
